fate/__init__.py
fate/_info.py
fate/arch/__init__.py
fate/arch/_standalone.py
fate/arch/abc/__init__.py
fate/arch/abc/_federation.py
fate/arch/abc/_party.py
fate/arch/abc/_table.py
fate/arch/computing/__init__.py
fate/arch/computing/_profile.py
fate/arch/computing/_type.py
fate/arch/computing/eggroll/__init__.py
fate/arch/computing/eggroll/_csession.py
fate/arch/computing/eggroll/_table.py
fate/arch/computing/eggroll/_type.py
fate/arch/computing/spark/__init__.py
fate/arch/computing/spark/_csession.py
fate/arch/computing/spark/_materialize.py
fate/arch/computing/spark/_table.py
fate/arch/computing/standalone/__init__.py
fate/arch/computing/standalone/_csession.py
fate/arch/computing/standalone/_table.py
fate/arch/computing/standalone/_type.py
fate/arch/context/__init__.py
fate/arch/context/_cipher.py
fate/arch/context/_context.py
fate/arch/context/_federation.py
fate/arch/context/_metrics.py
fate/arch/context/_namespace.py
fate/arch/dataframe/__init__.py
fate/arch/dataframe/_dataframe.py
fate/arch/dataframe/_frame_reader.py
fate/arch/dataframe/conf/__init__.py
fate/arch/dataframe/conf/default_config.py
fate/arch/dataframe/entity/__init__.py
fate/arch/dataframe/entity/types.py
fate/arch/dataframe/io/__init__.py
fate/arch/dataframe/io/_json_schema.py
fate/arch/dataframe/io/_json_serialization.py
fate/arch/dataframe/manager/__init__.py
fate/arch/dataframe/manager/block_manager.py
fate/arch/dataframe/manager/data_manager.py
fate/arch/dataframe/manager/schema_manager.py
fate/arch/dataframe/manager/utils/__init__.py
fate/arch/dataframe/manager/utils/_anonymous_generator.py
fate/arch/dataframe/ops/__init__.py
fate/arch/dataframe/ops/_activation.py
fate/arch/dataframe/ops/_apply_row.py
fate/arch/dataframe/ops/_arithmetic.py
fate/arch/dataframe/ops/_cmp.py
fate/arch/dataframe/ops/_compress_block.py
fate/arch/dataframe/ops/_data_overview.py
fate/arch/dataframe/ops/_dimension_scaling.py
fate/arch/dataframe/ops/_encoder.py
fate/arch/dataframe/ops/_field_extract.py
testfate-2.0.0b0.dist-info/METADATA
testfate-2.0.0b0.dist-info/WHEEL
testfate-2.0.0b0.dist-info/top_level.txt
testfate-2.0.0b0.dist-info/RECORD
