Metadata-Version: 2.1
Name: testfate
Version: 2.0.0b0
Home-page: https://fate.fedai.org/
Author: FederatedAI
Author-email: contact@FedAI.org
License: Apache-2.0 License
Keywords: federated learning
Requires-Python: >=3.8
Requires-Dist: lmdb (==1.3.0)
Requires-Dist: torch (==1.13.1)
Requires-Dist: fate-utils
Requires-Dist: pydantic (==1.10.12)
Requires-Dist: cloudpickle (==2.1.0)
Requires-Dist: click
Requires-Dist: ruamel.yaml (==0.16)
Requires-Dist: scikit-learn (==1.0.1)
Requires-Dist: numpy
Requires-Dist: pandas
Requires-Dist: transformers
Requires-Dist: accelerate
Requires-Dist: beautifultable
Requires-Dist: requests
Requires-Dist: grpcio
Requires-Dist: protobuf
Provides-Extra: all
Requires-Dist: pyfate[eggroll,pulsar,rabbitmq,spark] ; extra == 'all'
Provides-Extra: eggroll
Requires-Dist: grpcio (==1.46.3) ; extra == 'eggroll'
Requires-Dist: grpcio-tools (==1.46.3) ; extra == 'eggroll'
Requires-Dist: numba (==0.56.4) ; extra == 'eggroll'
Requires-Dist: protobuf (==3.19.6) ; extra == 'eggroll'
Requires-Dist: mmh3 (==3.0.0) ; extra == 'eggroll'
Requires-Dist: cachetools (>=3.0.0) ; extra == 'eggroll'
Requires-Dist: cloudpickle (==2.1.0) ; extra == 'eggroll'
Requires-Dist: psutil (>=5.7.0) ; extra == 'eggroll'
Provides-Extra: pulsar
Requires-Dist: urllib3 (==1.26.5) ; extra == 'pulsar'
Requires-Dist: pulsar-client (==2.10.2) ; (sys_platform != "darwin") and extra == 'pulsar'
Requires-Dist: pulsar-client (==2.10.1) ; (sys_platform == "darwin") and extra == 'pulsar'
Provides-Extra: rabbitmq
Requires-Dist: pika (==1.2.1) ; extra == 'rabbitmq'
Provides-Extra: spark
Requires-Dist: pyspark ; extra == 'spark'
